<metadata>
  <!--
  This sample removes the class: android.support.v4.content.AsyncTaskLoader.LoadTask:
  <remove-node path="/api/package[@name='android.support.v4.content']/class[@name='AsyncTaskLoader.LoadTask']" />
  
  This sample removes the method: android.support.v4.content.CursorLoader.loadInBackground:
  <remove-node path="/api/package[@name='android.support.v4.content']/class[@name='CursorLoader']/method[@name='loadInBackground']" />
  -->
  <remove-node path="/api/package[@name='com.google.protobuf']/class[@name='AbstractMessageLite']" />
  <remove-node path="/api/package[@name='com.google.protobuf']/class[@name='AbstractParser']" />
  <remove-node path="/api/package[@name='com.google.protobuf']/class[@name='Any']" />
  <remove-node path="/api/package[@name='com.google.protobuf']/class[@name='AnyProto']" />
  <remove-node path="/api/package[@name='com.google.protobuf']/class[@name='Api']" />
  <remove-node path="/api/package[@name='com.google.protobuf']/class[@name='ApiProto']" />
  <remove-node path="/api/package[@name='com.google.protobuf']/class[@name='BoolValue']" />
  <remove-node path="/api/package[@name='com.google.protobuf']/class[@name='ByteOutput']" />
  <remove-node path="/api/package[@name='com.google.protobuf']/class[@name='ByteString']" />
  <remove-node path="/api/package[@name='com.google.protobuf']/class[@name='BytesValue']" />
  <remove-node path="/api/package[@name='com.google.protobuf']/class[@name='CodedInputStream']" />
  <remove-node path="/api/package[@name='com.google.protobuf']/class[@name='CodedOutputStream']" />
  <remove-node path="/api/package[@name='com.google.protobuf']/class[@name='DescriptorProtos']" />
  <remove-node path="/api/package[@name='com.google.protobuf']/class[@name='DoubleValue']" />
  <remove-node path="/api/package[@name='com.google.protobuf']/class[@name='Duration']" />
  <remove-node path="/api/package[@name='com.google.protobuf']/class[@name='DurationProto']" />
  <remove-node path="/api/package[@name='com.google.protobuf']/class[@name='Empty']" />
  <remove-node path="/api/package[@name='com.google.protobuf']/class[@name='EmptyProto']" />
  <remove-node path="/api/package[@name='com.google.protobuf']/class[@name='Enum']" />
  <remove-node path="/api/package[@name='com.google.protobuf']/class[@name='EnumValue']" />
  <remove-node path="/api/package[@name='com.google.protobuf']/class[@name='ExtensionLite']" />
  <remove-node path="/api/package[@name='com.google.protobuf']/class[@name='ExtensionRegistryLite']" />
  <remove-node path="/api/package[@name='com.google.protobuf']/class[@name='Field']" />
  <remove-node path="/api/package[@name='com.google.protobuf']/class[@name='FieldMask']" />
  <remove-node path="/api/package[@name='com.google.protobuf']/class[@name='FieldMaskProto']" />
  <remove-node path="/api/package[@name='com.google.protobuf']/class[@name='FieldType']" />
  <remove-node path="/api/package[@name='com.google.protobuf']/class[@name='FloatValue']" />
  <remove-node path="/api/package[@name='com.google.protobuf']/class[@name='GeneratedMessageLite']" />
  <remove-node path="/api/package[@name='com.google.protobuf']/interface[@name='AnyOrBuilder']" />
  <remove-node path="/api/package[@name='com.google.protobuf']/interface[@name='ApiOrBuilder']" />
  <remove-node path="/api/package[@name='com.google.protobuf']/interface[@name='BoolValueOrBuilder']" />
  <remove-node path="/api/package[@name='com.google.protobuf']/interface[@name='BytesValueOrBuilder']" />
  <remove-node path="/api/package[@name='com.google.protobuf']/interface[@name='DoubleValueOrBuilder']" />
  <remove-node path="/api/package[@name='com.google.protobuf']/interface[@name='DurationOrBuilder']" />
  <remove-node path="/api/package[@name='com.google.protobuf']/interface[@name='EmptyOrBuilder']" />
  <remove-node path="/api/package[@name='com.google.protobuf']/interface[@name='EnumOrBuilder']" />
  <remove-node path="/api/package[@name='com.google.protobuf']/interface[@name='EnumValueOrBuilder']" />
  <remove-node path="/api/package[@name='com.google.protobuf']/interface[@name='ExperimentalApi']" />
  <remove-node path="/api/package[@name='com.google.protobuf']/interface[@name='FieldMaskOrBuilder']" />
  <remove-node path="/api/package[@name='com.google.protobuf']/interface[@name='FieldOrBuilder']" />
  <remove-node path="/api/package[@name='com.google.protobuf']/interface[@name='FloatValueOrBuilder']" />
  <remove-node path="/api/package[@name='com.google.protobuf']/interface[@name='Int32ValueOrBuilder']" />
  <remove-node path="/api/package[@name='com.google.protobuf']/interface[@name='Int64ValueOrBuilder']" />
  <remove-node path="/api/package[@name='com.google.protobuf']/interface[@name='LazyStringList']" />
  <remove-node path="/api/package[@name='com.google.protobuf']/interface[@name='ListValueOrBuilder']" />
  <remove-node path="/api/package[@name='com.google.protobuf']/interface[@name='MessageLite']" />
  <remove-node path="/api/package[@name='com.google.protobuf']/interface[@name='MessageLiteOrBuilder']" />
  <remove-node path="/api/package[@name='com.google.protobuf']/interface[@name='MethodOrBuilder']" />
  <remove-node path="/api/package[@name='com.google.protobuf']/interface[@name='MixinOrBuilder']" />
  <remove-node path="/api/package[@name='com.google.protobuf']/interface[@name='OptionOrBuilder']" />
  <remove-node path="/api/package[@name='com.google.protobuf']/interface[@name='Parser']" />
  <remove-node path="/api/package[@name='com.google.protobuf']/interface[@name='ProtocolStringList']" />
  <remove-node path="/api/package[@name='com.google.protobuf']/interface[@name='SourceContextOrBuilder']" />
  <remove-node path="/api/package[@name='com.google.protobuf']/interface[@name='StringValueOrBuilder']" />
  <remove-node path="/api/package[@name='com.google.protobuf']/interface[@name='StructOrBuilder']" />
  <remove-node path="/api/package[@name='com.google.protobuf']/interface[@name='TimestampOrBuilder']" />
  <remove-node path="/api/package[@name='com.google.protobuf']/interface[@name='TypeOrBuilder']" />
  <remove-node path="/api/package[@name='com.google.protobuf']/interface[@name='UInt32ValueOrBuilder']" />
  <remove-node path="/api/package[@name='com.google.protobuf']/interface[@name='UInt64ValueOrBuilder']" />
  <remove-node path="/api/package[@name='com.google.protobuf']/interface[@name='ValueOrBuilder']" />
  <remove-node path="/api/package[@name='com.google.protobuf']/class[@name='Int32Value']" />
  <remove-node path="/api/package[@name='com.google.protobuf']/class[@name='Int64Value']" />
  <remove-node path="/api/package[@name='com.google.protobuf']/class[@name='InvalidProtocolBufferException']" />
  <remove-node path="/api/package[@name='com.google.protobuf']/class[@name='JavaFeaturesProto']" />
  <remove-node path="/api/package[@name='com.google.protobuf']/class[@name='JavaType']" />
  <remove-node path="/api/package[@name='com.google.protobuf']/class[@name='LazyField']" />
  <remove-node path="/api/package[@name='com.google.protobuf']/class[@name='LazyFieldLite']" />
  <remove-node path="/api/package[@name='com.google.protobuf']/class[@name='LazyStringArrayList']" />
  <remove-node path="/api/package[@name='com.google.protobuf']/class[@name='ListValue']" />
  <remove-node path="/api/package[@name='com.google.protobuf']/class[@name='MapEntryLite']" />
  <remove-node path="/api/package[@name='com.google.protobuf']/class[@name='MapFieldLite']" />
  <remove-node path="/api/package[@name='com.google.protobuf']/class[@name='Method']" />
  <remove-node path="/api/package[@name='com.google.protobuf']/class[@name='Mixin']" />
  <remove-node path="/api/package[@name='com.google.protobuf']/class[@name='NullValue']" />
  <remove-node path="/api/package[@name='com.google.protobuf']/class[@name='Option']" />
  <remove-node path="/api/package[@name='com.google.protobuf']/class[@name='ProtoSyntax']" />
  <remove-node path="/api/package[@name='com.google.protobuf']/class[@name='RuntimeVersion']" />
  <remove-node path="/api/package[@name='com.google.protobuf']/class[@name='SourceContext']" />
  <remove-node path="/api/package[@name='com.google.protobuf']/class[@name='SourceContextProto']" />
  <remove-node path="/api/package[@name='com.google.protobuf']/class[@name='StringValue']" />
  <remove-node path="/api/package[@name='com.google.protobuf']/class[@name='Struct']" />
  <remove-node path="/api/package[@name='com.google.protobuf']/class[@name='StructProto']" />
  <remove-node path="/api/package[@name='com.google.protobuf']/class[@name='Syntax']" />
  <remove-node path="/api/package[@name='com.google.protobuf']/class[@name='Timestamp']" />
  <remove-node path="/api/package[@name='com.google.protobuf']/class[@name='TimestampProto']" />
  <remove-node path="/api/package[@name='com.google.protobuf']/class[@name='Type']" />
  <remove-node path="/api/package[@name='com.google.protobuf']/class[@name='TypeProto']" />
  <remove-node path="/api/package[@name='com.google.protobuf']/class[@name='UInt32Value']" />
  <remove-node path="/api/package[@name='com.google.protobuf']/class[@name='UInt64Value']" />
  <remove-node path="/api/package[@name='com.google.protobuf']/class[@name='UninitializedMessageException']" />
  <remove-node path="/api/package[@name='com.google.protobuf']/class[@name='UnmodifiableLazyStringList']" />
  <remove-node path="/api/package[@name='com.google.protobuf']/class[@name='UnknownFieldSetLite']" />
  <remove-node path="/api/package[@name='com.google.protobuf']/class[@name='UnsafeByteOperations']" />
  <remove-node path="/api/package[@name='com.google.protobuf']/class[@name='Value']" />
  <remove-node path="/api/package[@name='com.google.protobuf']/class[@name='WireFormat']" />
  <remove-node path="/api/package[@name='com.google.protobuf']/class[@name='WrappersProto']" />

  <remove-node path="/api/package[@name='com.google.protobuf']/interface[@name='Internal.ProtobufList']" />
  <remove-node path="/api/package[@name='com.google.protobuf']/interface[@name='Internal.BooleanList']" />
  <remove-node path="/api/package[@name='com.google.protobuf']/interface[@name='Internal.DoubleList']" />
  <remove-node path="/api/package[@name='com.google.protobuf']/interface[@name='Internal.FloatList']" />
  <remove-node path="/api/package[@name='com.google.protobuf']/interface[@name='Internal.IntList']" />
  <remove-node path="/api/package[@name='com.google.protobuf']/interface[@name='Internal.LongList']" />
  <remove-node path="/api/package[@name='com.google.protobuf']/class[@name='Internal']/field[@name='EMPTY_BYTE_ARRAY']" />
  <remove-node path="/api/package[@name='com.google.protobuf']/class[@name='Internal']/field[@name='EMPTY_BYTE_BUFFER']" />
  <remove-node path="/api/package[@name='com.google.protobuf']/class[@name='Internal']/field[@name='EMPTY_CODED_INPUT_STREAM']" />
  <remove-node path="/api/package[@name='com.google.protobuf']/class[@name='Internal']/method[@name='byteArrayDefaultValue']" />
  <remove-node path="/api/package[@name='com.google.protobuf']/class[@name='Internal']/method[@name='byteBufferDefaultValue']" />
  <remove-node path="/api/package[@name='com.google.protobuf']/class[@name='Internal']/method[@name='bytesDefaultValue']" />
  <remove-node path="/api/package[@name='com.google.protobuf']/class[@name='Internal']/method[@name='stringDefaultValue']" />
  <remove-node path="/api/package[@name='com.google.protobuf']/class[@name='Internal']/method[@name='getDefaultInstance']" />
  <remove-node path="/api/package[@name='com.google.protobuf']/class[@name='Internal']/method[@name='isValidUtf8']" />
  <remove-node path="/api/package[@name='com.google.protobuf']/class[@name='Internal.IntListAdapter']" />
  <remove-node path="/api/package[@name='com.google.protobuf']/class[@name='Internal.MapAdapter']" />
</metadata>
